holodeck/__init__.py
holodeck/chat/__init__.py
holodeck/chat/executor.py
holodeck/chat/message.py
holodeck/chat/progress.py
holodeck/chat/session.py
holodeck/chat/streaming.py
holodeck/cli/__init__.py
holodeck/cli/exceptions.py
holodeck/cli/main.py
holodeck/cli/commands/__init__.py
holodeck/cli/commands/chat.py
holodeck/cli/commands/config.py
holodeck/cli/commands/init.py
holodeck/cli/commands/mcp.py
holodeck/cli/commands/serve.py
holodeck/cli/commands/test.py
holodeck/cli/utils/__init__.py
holodeck/cli/utils/project_init.py
holodeck/cli/utils/wizard.py
holodeck/config/__init__.py
holodeck/config/context.py
holodeck/config/defaults.py
holodeck/config/env_loader.py
holodeck/config/loader.py
holodeck/config/manager.py
holodeck/config/merge.py
holodeck/config/schema.py
holodeck/config/validator.py
holodeck/lib/__init__.py
holodeck/lib/errors.py
holodeck/lib/exceptions.py
holodeck/lib/file_processor.py
holodeck/lib/logging_config.py
holodeck/lib/logging_utils.py
holodeck/lib/structured_loader.py
holodeck/lib/template_engine.py
holodeck/lib/text_chunker.py
holodeck/lib/validation.py
holodeck/lib/vector_store.py
holodeck/lib/evaluators/__init__.py
holodeck/lib/evaluators/azure_ai.py
holodeck/lib/evaluators/base.py
holodeck/lib/evaluators/nlp_metrics.py
holodeck/lib/evaluators/param_spec.py
holodeck/lib/evaluators/deepeval/__init__.py
holodeck/lib/evaluators/deepeval/answer_relevancy.py
holodeck/lib/evaluators/deepeval/base.py
holodeck/lib/evaluators/deepeval/config.py
holodeck/lib/evaluators/deepeval/contextual_precision.py
holodeck/lib/evaluators/deepeval/contextual_recall.py
holodeck/lib/evaluators/deepeval/contextual_relevancy.py
holodeck/lib/evaluators/deepeval/errors.py
holodeck/lib/evaluators/deepeval/faithfulness.py
holodeck/lib/evaluators/deepeval/geval.py
holodeck/lib/observability/__init__.py
holodeck/lib/observability/config.py
holodeck/lib/observability/errors.py
holodeck/lib/observability/instrumentation.py
holodeck/lib/observability/providers.py
holodeck_ai-0.3.2.dist-info/METADATA
holodeck_ai-0.3.2.dist-info/WHEEL
holodeck_ai-0.3.2.dist-info/entry_points.txt
holodeck_ai-0.3.2.dist-info/licenses/LICENSE
holodeck_ai-0.3.2.dist-info/RECORD
