Metadata-Version: 2.4
Name: holodeck-ai
Version: 0.3.2
Summary: HoloDeck - Experimentation-driven agent experimentation and deployment
Author-email: Justin Barias <justinbarias@live.com>
License-File: LICENSE
Requires-Python: >=3.10
Requires-Dist: absl-py<3.0.0,>=2.3.1
Requires-Dist: ag-ui-protocol<1.0.0,>=0.1.10
Requires-Dist: aiofiles<26.0.0,>=25.1.0
Requires-Dist: anthropic<0.73.0,>=0.72.0
Requires-Dist: azure-ai-evaluation<2.0.0,>=1.13.0
Requires-Dist: click<9.0.0,>=8.0.0
Requires-Dist: cryptography<47.0.0,>=46.0.2
Requires-Dist: deepeval<4.0.0,>=3.0.0
Requires-Dist: evaluate<0.5.0,>=0.4.6
Requires-Dist: fastapi<1.0.0,>=0.115.0
Requires-Dist: inquirerpy<0.4.0,>=0.3.4
Requires-Dist: jinja2<4.0.0,>=3.0.0
Requires-Dist: jsonschema<5.0.0,>=4.0.0
Requires-Dist: markitdown[all]<0.2.0,>=0.1.4
Requires-Dist: mcp>=1.23
Requires-Dist: mkdocs-material<10.0.0,>=9.6.22
Requires-Dist: ml-dtypes<0.5.0,>=0.4.0
Requires-Dist: ollama<1.0,>=0.4
Requires-Dist: opentelemetry-exporter-otlp-proto-grpc<2.0.0,>=1.20.0
Requires-Dist: opentelemetry-exporter-otlp-proto-http<2.0.0,>=1.20.0
Requires-Dist: opentelemetry-sdk<2.0.0,>=1.20.0
Requires-Dist: pydantic>=2.0.0
Requires-Dist: pypdf<7.0.0,>=6.3.0
Requires-Dist: python-dateutil>=2.8.0
Requires-Dist: python-dotenv>=1.0.0
Requires-Dist: python-ulid<4.0.0,>=3.1.0
Requires-Dist: pyyaml>=6.0.0
Requires-Dist: requests<3.0.0,>=2.32.5
Requires-Dist: rouge-score<0.2.0,>=0.1.2
Requires-Dist: sacrebleu<3.0.0,>=2.5.1
Requires-Dist: semantic-kernel<2.0.0,>=1.37.1
Requires-Dist: twine<7.0.0,>=6.2.0
Requires-Dist: urllib3<3.0.0,>=2.6.0
Requires-Dist: uvicorn[standard]<1.0.0,>=0.34.0
Requires-Dist: werkzeug>=3.1.4
Provides-Extra: chromadb
Requires-Dist: chromadb<1.1,>=0.5; extra == 'chromadb'
Provides-Extra: dev
Requires-Dist: bandit[toml]>=1.8.0; extra == 'dev'
Requires-Dist: black>=23.0.0; extra == 'dev'
Requires-Dist: detect-secrets>=1.4.0; extra == 'dev'
Requires-Dist: mkdocstrings[python]>=0.25.0; extra == 'dev'
Requires-Dist: mypy>=1.13.0; extra == 'dev'
Requires-Dist: pre-commit>=3.3.0; extra == 'dev'
Requires-Dist: pytest-asyncio>=0.21.0; extra == 'dev'
Requires-Dist: pytest-cov>=4.1.0; extra == 'dev'
Requires-Dist: pytest-mock>=3.11.0; extra == 'dev'
Requires-Dist: pytest-xdist>=3.8.0; extra == 'dev'
Requires-Dist: pytest>=7.4.0; extra == 'dev'
Requires-Dist: ruff>=0.1.0; extra == 'dev'
Requires-Dist: safety>=3.0.0; extra == 'dev'
Requires-Dist: tox>=4.0.0; extra == 'dev'
Requires-Dist: types-pyyaml>=6.0.12; extra == 'dev'
Provides-Extra: otel-all
Requires-Dist: azure-monitor-opentelemetry-exporter<2.0.0,>=1.0.0b24; extra == 'otel-all'
Requires-Dist: opentelemetry-exporter-prometheus<1.0.0,>=0.60b0; extra == 'otel-all'
Requires-Dist: prometheus-client<1.0.0,>=0.17.0; extra == 'otel-all'
Provides-Extra: otel-azmon
Requires-Dist: azure-monitor-opentelemetry-exporter<2.0.0,>=1.0.0b24; extra == 'otel-azmon'
Provides-Extra: otel-prometheus
Requires-Dist: opentelemetry-exporter-prometheus<1.0.0,>=0.60b0; extra == 'otel-prometheus'
Requires-Dist: prometheus-client<1.0.0,>=0.17.0; extra == 'otel-prometheus'
Provides-Extra: pinecone
Requires-Dist: pinecone[asyncio,grpc]~=7.0; extra == 'pinecone'
Provides-Extra: postgres
Requires-Dist: psycopg[binary,pool]~=3.2; extra == 'postgres'
Provides-Extra: qdrant
Requires-Dist: qdrant-client~=1.9; extra == 'qdrant'
Provides-Extra: vectorstores
Requires-Dist: chromadb<1.1,>=0.5; extra == 'vectorstores'
Requires-Dist: pinecone[asyncio,grpc]~=7.0; extra == 'vectorstores'
Requires-Dist: psycopg[binary,pool]~=3.2; extra == 'vectorstores'
Requires-Dist: qdrant-client~=1.9; extra == 'vectorstores'
